rebecca/__init__.py
rebecca/api.py
rebecca/enums.py
rebecca/models.py
rebecca/utils.py
rebecca_api-0.1.5.dist-info/METADATA
rebecca_api-0.1.5.dist-info/WHEEL
rebecca_api-0.1.5.dist-info/RECORD
