Metadata-Version: 2.4
Name: rebecca-api
Version: 0.1.5
Summary: Add your description here
Requires-Python: >=3.12
Requires-Dist: datetime>=5.5
Requires-Dist: httpx>=0.28.1
Requires-Dist: paramiko>=4.0.0
Requires-Dist: pydantic>=2.12.0
Requires-Dist: sshtunnel>=0.4.0
